labelimg2_zh/__init__.py
labelimg2_zh/labelImg.py
labelimg2_zh/img/advanced-settings.svg
labelimg2_zh/img/auto-adjust.svg
labelimg2_zh/img/bars.svg
labelimg2_zh/img/batch-processing.svg
labelimg2_zh/img/bucket.svg
labelimg2_zh/img/cancel2.svg
labelimg2_zh/img/close-hover.svg
labelimg2_zh/img/close-tab-hover-light.svg
labelimg2_zh/img/close-tab-light.svg
labelimg2_zh/img/close-white-hover.svg
labelimg2_zh/img/close-white.svg
labelimg2_zh/img/close.svg
labelimg2_zh/img/copy.svg
labelimg2_zh/img/crop-invert-checked.svg
labelimg2_zh/img/crop-invert.svg
labelimg2_zh/img/crop.svg
labelimg2_zh/img/dir.svg
labelimg2_zh/img/display-settings.svg
labelimg2_zh/img/display.svg
labelimg2_zh/img/down-white.svg
labelimg2_zh/img/down.svg
labelimg2_zh/img/downloaded.svg
labelimg2_zh/img/dummy-img.svg
labelimg2_zh/img/dummy.svg
labelimg2_zh/img/export.svg
labelimg2_zh/img/exposure.svg
labelimg2_zh/img/filter-disabled.svg
labelimg2_zh/img/filter.svg
labelimg2_zh/img/find.svg
labelimg2_zh/img/fit-width.svg
labelimg2_zh/img/flip-horizontal.svg
labelimg2_zh/img/flip-vertical.svg
labelimg2_zh/img/fullscreen.svg
labelimg2_zh/img/gradient-reset.svg
labelimg2_zh/img/grayscale.svg
labelimg2_zh/img/info.svg
labelimg2_zh/img/invert.svg
labelimg2_zh/img/landscape.svg
labelimg2_zh/img/loading.svg
labelimg2_zh/img/location.svg
labelimg2_zh/img/lock-unlocked.svg
labelimg2_zh/img/lock.svg
labelimg2_zh/img/manipulation.svg
labelimg2_zh/img/minus.svg
labelimg2_zh/img/next.svg
labelimg2_zh/img/nofilter.svg
labelimg2_zh/img/nomacs-bg.svg
labelimg2_zh/img/nomacs.svg
labelimg2_zh/img/normalize.svg
labelimg2_zh/img/open.svg
labelimg2_zh/img/pan-checked.svg
labelimg2_zh/img/pan.svg
labelimg2_zh/img/pan_checked.svg
labelimg2_zh/img/paste.svg
labelimg2_zh/img/pause.svg
labelimg2_zh/img/pin-checked.svg
labelimg2_zh/img/pin.svg
labelimg2_zh/img/pipette.svg
labelimg2_zh/img/play.svg
labelimg2_zh/img/player-back.svg
labelimg2_zh/img/player-next.svg
labelimg2_zh/img/player-pause.svg
labelImg2_zh-1.2.dist-info/METADATA
labelImg2_zh-1.2.dist-info/WHEEL
labelImg2_zh-1.2.dist-info/entry_points.txt
labelImg2_zh-1.2.dist-info/top_level.txt
labelImg2_zh-1.2.dist-info/RECORD
