Metadata-Version: 2.1
Name: labelImg2-zh
Version: 1.2
Summary: LabelImg2 is a graphical image annotation tool and label object bounding boxes in images
Home-page: https://github.com/chinakook/labelImg2
Author: TzuTa Lin
Author-email: tzu.ta.lin@gmail.com
License: MIT license
Keywords: labelImg labelTool development annotation deeplearning
Requires-Dist: lxml
